azure/mgmt/oep/__init__.py
azure/mgmt/oep/_configuration.py
azure/mgmt/oep/_open_energy_platform_management_service_apis.py
azure/mgmt/oep/_patch.py
azure/mgmt/oep/_serialization.py
azure/mgmt/oep/_vendor.py
azure/mgmt/oep/_version.py
azure/mgmt/oep/py.typed
azure/mgmt/oep/aio/__init__.py
azure/mgmt/oep/aio/_configuration.py
azure/mgmt/oep/aio/_open_energy_platform_management_service_apis.py
azure/mgmt/oep/aio/_patch.py
azure/mgmt/oep/aio/operations/__init__.py
azure/mgmt/oep/aio/operations/_energy_services_operations.py
azure/mgmt/oep/aio/operations/_locations_operations.py
azure/mgmt/oep/aio/operations/_operations.py
azure/mgmt/oep/aio/operations/_patch.py
azure/mgmt/oep/models/__init__.py
azure/mgmt/oep/models/_models_py3.py
azure/mgmt/oep/models/_open_energy_platform_management_service_apis_enums.py
azure/mgmt/oep/models/_patch.py
azure/mgmt/oep/operations/__init__.py
azure/mgmt/oep/operations/_energy_services_operations.py
azure/mgmt/oep/operations/_locations_operations.py
azure/mgmt/oep/operations/_operations.py
azure/mgmt/oep/operations/_patch.py
azure_mgmt_oep-1.0.0b2.dist-info/LICENSE
azure_mgmt_oep-1.0.0b2.dist-info/METADATA
azure_mgmt_oep-1.0.0b2.dist-info/WHEEL
azure_mgmt_oep-1.0.0b2.dist-info/top_level.txt
azure_mgmt_oep-1.0.0b2.dist-info/RECORD
